ncflag/__init__.py
ncflag/__main__.py
ncflag/cli.py
ncflag/flag_wrapper.py
ncflag-0.3.3.dist-info/LICENSE
ncflag-0.3.3.dist-info/METADATA
ncflag-0.3.3.dist-info/WHEEL
ncflag-0.3.3.dist-info/entry_points.txt
ncflag-0.3.3.dist-info/top_level.txt
ncflag-0.3.3.dist-info/RECORD
