Metadata-Version: 2.1
Name: ncflag
Version: 0.3.3
Summary: Utility and library to interface with CF-Compliant NetCDF flag variables.
Home-page: https://github.com/5tefan/ncflag
Author: Stefan Codrescu
Author-email: stefan.codrescu@noaa.gov
Classifier: Development Status :: 4 - Beta
Classifier: Intended Audience :: Science/Research
Classifier: Programming Language :: Python :: 3.7
Classifier: Programming Language :: Python :: 3.8
Classifier: License :: OSI Approved :: MIT License
Classifier: Operating System :: OS Independent
License-File: LICENSE
Requires-Dist: click
Requires-Dist: numpy
Requires-Dist: netCDF4
